torchot/__init__.py
torchot/sinkhorn.py
torchot-0.0.1.dist-info/LICENSE
torchot-0.0.1.dist-info/METADATA
torchot-0.0.1.dist-info/WHEEL
torchot-0.0.1.dist-info/top_level.txt
torchot-0.0.1.dist-info/RECORD
